iris_ep.py
iris/__init__.py
iris_embedded_python/__init__.py
iris_embedded_python/__init__.pyi
iris_embedded_python/iris_ipm.py
iris_embedded_python/iris_ipm.pyi
iris_embedded_python/iris_utils.py
iris_embedded_python_wrapper-0.2.5.dist-info/licenses/LICENSE
iris_utils/_cli.py
iris_utils/_find_libpyton.py
iris_embedded_python_wrapper-0.2.5.dist-info/METADATA
iris_embedded_python_wrapper-0.2.5.dist-info/WHEEL
iris_embedded_python_wrapper-0.2.5.dist-info/entry_points.txt
iris_embedded_python_wrapper-0.2.5.dist-info/top_level.txt
iris_embedded_python_wrapper-0.2.5.dist-info/RECORD
