Metadata-Version: 2.4
Name: iris-embedded-python-wrapper
Version: 0.2.5
Summary: Wrapper for embedded python on InterSystems IRIS
Author-email: grongier <guillaume.rongier@intersystems.com>
License: MIT License
Project-URL: homepage, https://github.com/grongierisc/iris-embedded-python-wrapper
Project-URL: documentation, https://github.com/grongierisc/iris-embedded-python-wrapper/blob/master/README.md
Project-URL: repository, https://github.com/grongierisc/iris-embedded-python-wrapper
Project-URL: issues, https://github.com/grongierisc/iris-embedded-python-wrapper/issues
Keywords: iris,intersystems,python,embedded
Classifier: Development Status :: 5 - Production/Stable
Classifier: Intended Audience :: Developers
Classifier: License :: OSI Approved :: MIT License
Classifier: Operating System :: OS Independent
Classifier: Programming Language :: Python :: 3.9
Classifier: Programming Language :: Python :: 3.10
Classifier: Programming Language :: Python :: 3.11
Classifier: Programming Language :: Python :: 3.12
Classifier: Topic :: Utilities
Requires-Python: >=3.8
License-File: LICENSE
Dynamic: license-file
